dumb_pypi/__init__.py
dumb_pypi/main.py
dumb_pypi/templates/_base.html
dumb_pypi/templates/changelog.html
dumb_pypi/templates/index.html
dumb_pypi/templates/package.html
dumb_pypi/templates/simple.html
dumbr_pypi-1.13.0.dist-info/LICENSE
dumbr_pypi-1.13.0.dist-info/METADATA
dumbr_pypi-1.13.0.dist-info/WHEEL
dumbr_pypi-1.13.0.dist-info/entry_points.txt
dumbr_pypi-1.13.0.dist-info/top_level.txt
dumbr_pypi-1.13.0.dist-info/RECORD
