Metadata-Version: 2.1
Name: dumbr-pypi
Version: 1.13.0
Home-page: https://github.com/chriskuehl/dumb-pypi
Author: Chris Kuehl
Author-email: ckuehl@ckuehl.me
License: Apache License 2.0
Classifier: License :: OSI Approved :: Apache Software License
Classifier: Programming Language :: Python :: 3
Classifier: Programming Language :: Python :: 3 :: Only
Classifier: Programming Language :: Python :: Implementation :: CPython
Requires-Python: >=3.7
License-File: LICENSE
Requires-Dist: jinja2
Requires-Dist: packaging (>=20.9)
